<LanguageData>
	<!-- Defs\WorkGiverDefs\WorkGivers.xml -->
	<!-- EN: reload turrets -->
	<ReloadTurrets.label>recargar torretas</ReloadTurrets.label>
	<!-- EN: reload -->
	<ReloadTurrets.verb>recargar</ReloadTurrets.verb>
	<!-- EN: reloading -->
	<ReloadTurrets.gerund>recargando</ReloadTurrets.gerund>
	
	<!-- EN: reload ammo container -->
	<ReloadAutoLoader.label>recargar contenedor de munición</ReloadAutoLoader.label>
	<!-- EN: reload -->
	<ReloadAutoLoader.verb>recargar</ReloadAutoLoader.verb>
	<!-- EN: reloading -->
	<ReloadAutoLoader.gerund>recargando</ReloadAutoLoader.gerund>
	
	<!-- EN: make ammo -->
	<DoBillsAmmoBench.label>hacer munición</DoBillsAmmoBench.label>
	<!-- EN: produce ammo -->
	<DoBillsAmmoBench.verb>producir munición</DoBillsAmmoBench.verb>
	<!-- EN: producing ammo at -->
	<DoBillsAmmoBench.gerund>produciendo munición en</DoBillsAmmoBench.gerund>
	
	<!-- EN: modify weapons -->
	<ModifyWeapons.label>modificar armas</ModifyWeapons.label>
	<!-- EN: attach attachments -->
	<ModifyWeapons.verb>adjuntar accesorios</ModifyWeapons.verb>
	<!-- EN: applying modifications at -->
	<ModifyWeapons.gerund>aplicando modificaciones en</ModifyWeapons.gerund>
</LanguageData>