<LanguageData>
	<!-- Defs\ResearchProjectDefs\ResearchProjects_Turrets.xml -->
	<!-- EN: heavy weapons -->
	<CE_TurretHeavyWeapons.label>armas pesadas</CE_TurretHeavyWeapons.label>
	<!-- EN: Allows you to assemble high-caliber weapons, automatic grenade launchers and artillery. -->
	<CE_TurretHeavyWeapons.description>Permite ensamblar armas de alto calibre, lanzagranadas automaticos y artilleria.</CE_TurretHeavyWeapons.description>
	<!-- EN: 
		<li>subject->heavy-duty barrels</li>
		<li>subject->high-caliber emplacements</li>
		<li>subject_story->hardened components to withstand enormously high pressures</li>
		<li>subject_story->survived a years-long siege on a war-world</li>
		<li>subject_story->worked in a factory that manufactured artillery barrels</li>
		<li>subject_gerund->building heavy emplacements</li>
	 -->
	<CE_TurretHeavyWeapons.generalRules.rulesStrings>
		<li>subject->cañones reforzados</li>
		<li>subject->emplazamientos de alto calibre</li>
		<li>subject_story->endurecio componentes para soportar presiones enormemente altas</li>
		<li>subject_story->sobrevivio a un asedio de anos en un mundo en guerra</li>
		<li>subject_story->trabajo en una fabrica que producia cañones de artilleria</li>
		<li>subject_gerund->construyendo emplazamientos pesados</li>
	</CE_TurretHeavyWeapons.generalRules.rulesStrings>
	
	<!-- EN: heavy auto turrets -->
	<CE_HeavyTurret.label>torretas automaticas pesadas</CE_HeavyTurret.label>
	<!-- EN: Learn to construct heavy auto-turrets. -->
	<CE_HeavyTurret.description>Aprende a construir torretas automaticas pesadas.</CE_HeavyTurret.description>
	<!-- EN: 
		<li>subject->heavy autoturrets</li>
		<li>subject_story->optimized automated fire-control systems for long range engagements</li>
		<li>subject_story->developed improved electronic IFF protocols</li>
		<li>subject_story->worked for an urbworld firm that produced mechanoid sensory systems</li>
		<li>subject_gerund->automating heavy emplacements</li>
	 -->
	<CE_HeavyTurret.generalRules.rulesStrings>
		<li>subject->torretas automaticas pesadas</li>
		<li>subject_story->optimizo sistemas automatizados de control de fuego para enfrentamientos de largo alcance</li>
		<li>subject_story->desarrollo protocolos electronicos IFF mejorados</li>
		<li>subject_story->trabajo para una empresa de mundo urbano que producia sistemas sensoriales de mecanoides</li>
		<li>subject_gerund->automatizando emplazamientos pesados</li>
	</CE_HeavyTurret.generalRules.rulesStrings>
	
	<!-- EN: charge blaster turrets -->
	<CE_ChargeTurret.label>torretas blaster de carga</CE_ChargeTurret.label>
	<!-- EN: Learn to construct charge blaster turrets. -->
	<CE_ChargeTurret.description>Aprende a construir torretas blaster de carga.</CE_ChargeTurret.description>
	<!-- EN: 
		<li>subject->charge turrets</li>
		<li>subject_story->created denser power units for higher draw</li>
		<li>subject_story->explored the remnants of a toxic world battlefield</li>
		<li>subject_story->took part in a doomed assault against a mechanoid stronghold</li>
		<li>subject_gerund->building charged-shot turrets</li>
	 -->
	<CE_ChargeTurret.generalRules.rulesStrings>
		<li>subject->torretas de carga</li>
		<li>subject_story->creo unidades de energia mas densas para mayor consumo</li>
		<li>subject_story->exploro los restos de un campo de batalla en un mundo toxico</li>
		<li>subject_story->participo en un asalto condenado contra una fortaleza mecanoide</li>
		<li>subject_gerund->construyendo torretas de disparo cargado</li>
	</CE_ChargeTurret.generalRules.rulesStrings>
</LanguageData>